bytedgraphworks/__init__.py
bytedgraphworks-0.0.1.dist-info/METADATA
bytedgraphworks-0.0.1.dist-info/WHEEL
bytedgraphworks-0.0.1.dist-info/top_level.txt
bytedgraphworks-0.0.1.dist-info/RECORD
